mbonig_secret/__init__.py
mbonig_secret/py.typed
mbonig_secret/_jsii/__init__.py
mbonig_secret/_jsii/secret@0.0.5.jsii.tgz
mbonig.secret-0.0.5.dist-info/LICENSE
mbonig.secret-0.0.5.dist-info/METADATA
mbonig.secret-0.0.5.dist-info/WHEEL
mbonig.secret-0.0.5.dist-info/top_level.txt
mbonig.secret-0.0.5.dist-info/RECORD
