Metadata-Version: 2.1
Name: mbonig.secret
Version: 0.0.5
Summary: An AWS CDK construct for creating a secret in AWS Secrets Manager, without losing manually changed values.
Home-page: https://github.com/mbonig/secret.git
Author: Matthew Bonig<matthew.bonig@gmail.com>
License: MIT
Project-URL: Source, https://github.com/mbonig/secret.git
Classifier: Intended Audience :: Developers
Classifier: Operating System :: OS Independent
Classifier: Programming Language :: JavaScript
Classifier: Programming Language :: Python :: 3 :: Only
Classifier: Programming Language :: Python :: 3.8
Classifier: Programming Language :: Python :: 3.9
Classifier: Programming Language :: Python :: 3.10
Classifier: Programming Language :: Python :: 3.11
Classifier: Typing :: Typed
Classifier: Development Status :: 5 - Production/Stable
Classifier: License :: OSI Approved
Requires-Python: ~=3.8
License-File: LICENSE
Requires-Dist: aws-cdk-lib<3.0.0,>=2.181.1
Requires-Dist: constructs<11.0.0,>=10.1.203
Requires-Dist: jsii<2.0.0,>=1.108.0
Requires-Dist: publication>=0.0.3
Requires-Dist: typeguard<4.3.0,>=2.13.3
